ptsrvtester/__init__.py
ptsrvtester/_version.py
ptsrvtester/ptsrvtester.py
ptsrvtester/modules/__init__.py
ptsrvtester/modules/_base.py
ptsrvtester/modules/dhcp.py
ptsrvtester/modules/dns.py
ptsrvtester/modules/ftp.py
ptsrvtester/modules/imap.py
ptsrvtester/modules/ldap.py
ptsrvtester/modules/msrpc.py
ptsrvtester/modules/pop3.py
ptsrvtester/modules/smtp.py
ptsrvtester/modules/snmp.py
ptsrvtester/modules/ssh.py
ptsrvtester/modules/xrdp.py
ptsrvtester/modules/utils/__init__.py
ptsrvtester/modules/utils/blacklist_parser.py
ptsrvtester/modules/utils/helpers.py
ptsrvtester/ptntlmauth/__init__.py
ptsrvtester/ptntlmauth/_version.py
ptsrvtester/ptntlmauth/ptntlmauth.py
ptsrvtester-1.0.4.dist-info/licenses/LICENSE
ptsrvtester-1.0.4.dist-info/METADATA
ptsrvtester-1.0.4.dist-info/WHEEL
ptsrvtester-1.0.4.dist-info/entry_points.txt
ptsrvtester-1.0.4.dist-info/top_level.txt
ptsrvtester-1.0.4.dist-info/RECORD
