Metadata-Version: 2.4
Name: ptsrvtester
Version: 1.0.4
Summary: Application server penetration testing tool (Penterep tool)
Home-page: https://www.penterep.com/
Author: Penterep
Author-email: xvlkov03@vutbr.cz
License: GPLv3+
Classifier: Programming Language :: Python :: 3
Classifier: Programming Language :: Python :: Implementation :: CPython
Classifier: Environment :: Console
Classifier: Topic :: Security
Classifier: License :: OSI Approved :: GNU General Public License v3 or later (GPLv3+)
Requires-Python: >=3.12
License-File: LICENSE
Requires-Dist: cryptography>=42.0.8
Requires-Dist: dnspython>=2.7.0
Requires-Dist: impacket>=0.12.0
Requires-Dist: ldap3>=2.9.1
Requires-Dist: ptlibs<2,>=1.0.20
Requires-Dist: pysnmp>=7.1.20
Requires-Dist: python-whois>=0.9.5
Requires-Dist: paramiko>=4.0.0
Requires-Dist: beautifulsoup4>=4.14.0
Requires-Dist: httpx>=0.28.0
Requires-Dist: h2>=4.3.0
Requires-Dist: lxml>=6.0.0
Requires-Dist: ssh_audit>=3.3.0
Requires-Dist: ntlm-auth>=1.5.0
Requires-Dist: scapy>=2.6.1
Requires-Dist: dhcppython>=0.1.4
Requires-Dist: pillow>=12.0.0
Requires-Dist: python-xlib>=0.33
Requires-Dist: pynput>=1.8.0
Requires-Dist: XWindows>=0.0.7
Dynamic: author
Dynamic: author-email
Dynamic: classifier
Dynamic: description
Dynamic: description-content-type
Dynamic: home-page
Dynamic: license
Dynamic: license-file
Dynamic: requires-dist
Dynamic: requires-python
Dynamic: summary
